{"trial_id": "18", "hyperparameters": {"space": [{"class_name": "Float", "config": {"name": "dropout_rate_1", "default": 0.2, "conditions": [], "min_value": 0.2, "max_value": 0.5, "step": 0.1, "sampling": "linear"}}, {"class_name": "Float", "config": {"name": "dropout_rate_2", "default": 0.2, "conditions": [], "min_value": 0.2, "max_value": 0.5, "step": 0.1, "sampling": "linear"}}, {"class_name": "Int", "config": {"name": "units", "default": null, "conditions": [], "min_value": 256, "max_value": 512, "step": 128, "sampling": "linear"}}, {"class_name": "Choice", "config": {"name": "learning_rate", "default": 0.001, "conditions": [], "values": [0.001, 0.0001], "ordered": true}}], "values": {"dropout_rate_1": 0.2, "dropout_rate_2": 0.30000000000000004, "units": 256, "learning_rate": 0.001}}, "metrics": {"metrics": {"loss": {"direction": "min", "observations": [{"value": [0.01447701919823885], "step": 31}]}, "mae": {"direction": "min", "observations": [{"value": [0.08479693531990051], "step": 31}]}, "root_mean_squared_error": {"direction": "min", "observations": [{"value": [0.12032049149274826], "step": 31}]}, "val_loss": {"direction": "min", "observations": [{"value": [0.01239078864455223], "step": 31}]}, "val_mae": {"direction": "min", "observations": [{"value": [0.07779087871313095], "step": 31}]}, "val_root_mean_squared_error": {"direction": "min", "observations": [{"value": [0.11131391674280167], "step": 31}]}}}, "score": 0.01239078864455223, "best_step": 31, "status": "COMPLETED", "message": null}